ubertyped/__init__.py
ubertyped/mypy_plugin.py
ubertyped/py.typed
ubertyped-0.1.2.dist-info/LICENSE
ubertyped-0.1.2.dist-info/METADATA
ubertyped-0.1.2.dist-info/WHEEL
ubertyped-0.1.2.dist-info/RECORD
