Metadata-Version: 2.1
Name: ubertyped
Version: 0.1.2
Summary: Convert dataclass to TypedDict for fun and type safety 🪄
Home-page: https://github.com/ViliamV/ubertyped
License: MIT
Author: Viliam Valent
Author-email: hello@valent.email
Requires-Python: >=3.11,<4.0
Classifier: License :: OSI Approved :: MIT License
Classifier: Programming Language :: Python :: 3
Classifier: Programming Language :: Python :: 3.11
Classifier: Programming Language :: Python :: 3.12
Project-URL: Repository, https://github.com/ViliamV/ubertyped
